[
  {
    "short": "arts",
    "long": "Arts, Exhibits, & Expos",
    "meta": "artistic"
  },
  {
    "short": "outdoors",
    "long": "Outdoors",
    "meta": "active",
    "notes": "(hikes, nature walks, etc.)"
  },
  {
    "short": "festivals",
    "long": "Festivals & Parades",
    "meta": "other"
  },
  {
    "short": "food",
    "long": "Food & Drink",
    "meta": "eat"
  },
  {
    "short": "music",
    "long": "Music",
    "meta": "artistic"
  },
  {
    "short": "market",
    "long": "Markets",
    "meta": "other"
  },
  {
    "short": "athletic",
    "long": "Athletic and Aquatic Activities",
    "meta": "active",
    "notes": "(races, 5Ks, etc.)"
  }
]